LICENSE
README.md
pyproject.toml
setup.py
CoSpecPy/__init__.py
CoSpecPy/composite_helpers.py
CoSpecPy/composites.py
CoSpecPy/download.py
CoSpecPy.egg-info/PKG-INFO
CoSpecPy.egg-info/SOURCES.txt
CoSpecPy.egg-info/dependency_links.txt
CoSpecPy.egg-info/top_level.txt
CoSpecPy/data/example_speclist.txt
CoSpecPy/test/__init__.py
CoSpecPy/test/test_composites.py
CoSpecPy/test/test_download.py