Metadata-Version: 2.1
Name: CoSpecPy
Version: 0.4
Summary: Python Package for SDSS Composite Spectra
Home-page: https://github.com/jwpetley/CoSpecPy
Author: James Petley
Author-email: jwpetley@gmail.com
License: UNKNOWN
Platform: UNKNOWN
Requires-Python: >=3.6
License-File: LICENSE
